Metadata-Version: 2.1
Name: fastapi-signals
Version: 0.1.1
Summary: Signalling for FastAPI.
Home-page: https://github.com/henshalb/fastapi-signals.git
Author: Henshal B
Author-email: henshalb@gmail.com
License: MIT
Download-URL: https://github.com/henshalb/fastapi-signals/archive/refs/tags/v0.1.1.tar.gz
Keywords: fastapi,signals,fastapi-signals,background task
Platform: UNKNOWN
Classifier: Development Status :: 4 - Beta
Classifier: Intended Audience :: Developers
Classifier: Topic :: Software Development :: Build Tools
Classifier: License :: OSI Approved :: MIT License
Classifier: Programming Language :: Python :: 3
Classifier: Programming Language :: Python :: 3.4
Classifier: Programming Language :: Python :: 3.5
Classifier: Programming Language :: Python :: 3.6
Classifier: Programming Language :: Python :: 3.7
